catala/__init__.py
catala/runtime.py
catala_runtime-0.9.0.dist-info/METADATA
catala_runtime-0.9.0.dist-info/WHEEL
catala_runtime-0.9.0.dist-info/RECORD
